py1cmd-0.3.dist-info/WHEEL
py1cmd-0.3.dist-info/top_level.txt
py1cmd-0.3.dist-info/entry_points.txt
py1cmd-0.3.dist-info/METADATA
py1cmd-0.3.dist-info/DESCRIPTION.rst
py1cmd-0.3.dist-info/RECORD
py1cmd-0.3.dist-info/metadata.json
py1cmd-0.3.data/data/share/man/man1/py1.1
py1/__init__.py
py1/constants.py
py1/main.py
py1/user_code_template.py
py1/imports.py
py1/__main__.py
py1/curly.py
py1/runner.py
py1/template_reader.py
py1/tty.py
