Metadata-Version: 2.0
Name: py1cmd
Version: 0.3
Summary: Runs awk-like Python one-liners.
Home-page: http://py1.vleu.net/
Author: Brice Arnould
Author-email: unbrice@vleu.net
License: MIT
Keywords: scripting awk one-liner oneliner
Platform: UNKNOWN
Classifier: Development Status :: 4 - Beta
Classifier: License :: OSI Approved :: MIT License
Classifier: Intended Audience :: Developers
Classifier: Intended Audience :: System Administrators
Classifier: Topic :: Software Development :: Interpreters
Classifier: Topic :: System :: Shells
Classifier: Topic :: Text Processing :: Filters
Classifier: Environment :: Console
Classifier: Operating System :: OS Independent
Classifier: Programming Language :: Python :: 3
Classifier: Programming Language :: Python :: 3.3
Classifier: Programming Language :: Python :: 3.4
Classifier: Programming Language :: Python :: 3.5
Requires-Dist: pygments (>=0.10)
